setup.py
transformpy/__init__.py
transformpy/base.py
transformpy.egg-info/PKG-INFO
transformpy.egg-info/SOURCES.txt
transformpy.egg-info/dependency_links.txt
transformpy.egg-info/requires.txt
transformpy.egg-info/top_level.txt
transformpy/pipes/__init__.py
transformpy/pipes/clustering.py
transformpy/pipes/debug.py
transformpy/pipes/field.py
transformpy/pipes/hive.py
transformpy/pipes/pandas.py