Metadata-Version: 1.0
Name: transformpy
Version: 0.3.0
Summary: A general purpose python ETL/pipeline utility library, for use especially with Hive Streaming.
Home-page: UNKNOWN
Author: Matthew Wardrop
Author-email: matthew.wardrop@airbnb.com
License: UNKNOWN
Keywords: pipeline transform hive
Platform: UNKNOWN
